cryptofeed_werks/__init__.py
cryptofeed_werks/exchanges/__init__.py
cryptofeed_werks/exchanges/binance.py
cryptofeed_werks/exchanges/bitfinex.py
cryptofeed_werks/exchanges/bitflyer.py
cryptofeed_werks/exchanges/bitmex.py
cryptofeed_werks/exchanges/bybit.py
cryptofeed_werks/exchanges/coinbase.py
cryptofeed_werks/exchanges/upbit.py
cryptofeed_werks/feed.py
cryptofeed_werks/trades/__init__.py
cryptofeed_werks/trades/candles.py
cryptofeed_werks/trades/constants.py
cryptofeed_werks/trades/gcppubsub.py
cryptofeed_werks/trades/significant_trades.py
cryptofeed_werks/trades/trade_cluster.py
cryptofeed_werks/trades/trades.py
cryptofeed_werks/trades/utils.py
cryptofeed_werks/trades/window.py
cryptofeed_werks-0.1.6.dist-info/LICENSE
cryptofeed_werks-0.1.6.dist-info/METADATA
cryptofeed_werks-0.1.6.dist-info/WHEEL
cryptofeed_werks-0.1.6.dist-info/RECORD
