Metadata-Version: 2.1
Name: cryptofeed-werks
Version: 0.1.6
Summary: WebSocket subclasses, and experiments, for data from cryptocurrency exchanges
Home-page: https://github.com/globophobe/cryptofeed-werks
License: MIT
Keywords: cryptocurrency,trading
Author: Alex
Author-email: globophobe@gmail.com
Requires-Python: >=3.8,<4.0
Classifier: License :: OSI Approved :: MIT License
Classifier: Operating System :: OS Independent
Classifier: Programming Language :: Python :: 3
Classifier: Programming Language :: Python :: 3.8
Classifier: Programming Language :: Python :: 3.9
Classifier: Programming Language :: Python :: 3.10
Classifier: Programming Language :: Python :: 3.11
Provides-Extra: all
Provides-Extra: bigquery
Provides-Extra: httpx
Provides-Extra: pubsub
Requires-Dist: cryptofeed
Requires-Dist: google-cloud-bigquery ; extra == "all" or extra == "bigquery"
Requires-Dist: google-cloud-bigquery-storage ; extra == "all" or extra == "bigquery"
Requires-Dist: google-cloud-pubsub ; extra == "all" or extra == "pubsub"
Requires-Dist: httpx ; extra == "all" or extra == "httpx"
Requires-Dist: pandas
Project-URL: Repository, https://github.com/globophobe/cryptofeed-werks
